setup.cfg
setup.py
bin/agnosc
bin/agnosc.bat
bin/agnosrc-py
bin/agnosrc-py.bat
src/agnos_compiler/__init__.py
src/agnos_compiler/compat.py
src/agnos_compiler/compiler.py
src/agnos_compiler/idl_syntax.py
src/agnos_compiler/version.py
src/agnos_compiler.egg-info/PKG-INFO
src/agnos_compiler.egg-info/SOURCES.txt
src/agnos_compiler.egg-info/dependency_links.txt
src/agnos_compiler.egg-info/top_level.txt
src/agnos_compiler/langs/__init__.py
src/agnos_compiler/langs/clike.py
src/agnos_compiler/langs/cpp.py
src/agnos_compiler/langs/python.py
src/agnos_compiler/langs/xml.py
src/agnos_compiler/pysrcgen/__init__.py
src/agnos_compiler/pysrcgen/generator.py
src/agnos_compiler/pysrcgen/syntree.py
src/agnos_compiler/targets/__init__.py
src/agnos_compiler/targets/base.py
src/agnos_compiler/targets/cpp.py
src/agnos_compiler/targets/csharp.py
src/agnos_compiler/targets/htmldoc.py
src/agnos_compiler/targets/java.py
src/agnos_compiler/targets/jscript.py
src/agnos_compiler/targets/powershell.py
src/agnos_compiler/targets/python.py