Metadata-Version: 1.0
Name: agnos-compiler
Version: 1.0.2
Summary: Agnos Compiler Toolchain
Home-page: http://agnos.sourceforge.net
Author: Tomer Filiba
Author-email: tomerf@il.ibm.com
License: Apache License 2.0
Download-URL: http://www.sourceforge.net/projects/agnos/files/1.0.2
Platform: POSIX
Platform: Windows
Classifier: Development Status :: 4 - Beta
Classifier: Intended Audience :: Developers
Classifier: License :: OSI Approved :: Apache Software License
Classifier: Operating System :: OS Independent
Classifier: Programming Language :: C#
Classifier: Programming Language :: C++
Classifier: Programming Language :: Java
Classifier: Programming Language :: Python
Classifier: Topic :: Software Development :: Code Generators
Classifier: Topic :: Software Development :: Object Brokering
